setup.py
lib1.egg-info/PKG-INFO
lib1.egg-info/SOURCES.txt
lib1.egg-info/dependency_links.txt
lib1.egg-info/top_level.txt
p1/__init__.py