Metadata-Version: 1.0
Name: lib1
Version: 1.0
Summary: My first Python library
Home-page: UNKNOWN
Author: mm
Author-email: UNKNOWN
License: UNKNOWN
Platform: UNKNOWN
